wirepy/__init__.py
wirepy/cli.py
wirepy/migrations.py
wirepy/scaffold.py
wirepy/templates/.DS_Store
wirepy/templates/.env
wirepy/templates/README.md
wirepy/templates/__init__.py
wirepy/templates/main.py
wirepy/templates/requirements.txt
wirepy/templates/app/controllers/__init__.py
wirepy/templates/app/core/__init__.py
wirepy/templates/app/core/config.py
wirepy/templates/app/core/database.py
wirepy/templates/app/database/__init__.py
wirepy/templates/app/database/base.py
wirepy/templates/app/database/base_class.py
wirepy/templates/app/database/config.py
wirepy/templates/app/database/session.py
wirepy/templates/app/models/__init__.py
wirepy/templates/app/routes/__init__.py
wirepy/templates/app/routes/base.py
wirepy/templates/app/routes/v1/route_user.py
wirepy/templates/app/schemas/__init__.py
wirepy/templates/app/schemas/user_schema.py
wirepy/templates/app/services/__init__.py
wirepy-0.2.3.dist-info/licenses/LICENSE
wirepy-0.2.3.dist-info/METADATA
wirepy-0.2.3.dist-info/WHEEL
wirepy-0.2.3.dist-info/entry_points.txt
wirepy-0.2.3.dist-info/top_level.txt
wirepy-0.2.3.dist-info/RECORD
