Metadata-Version: 2.4
Name: wirepy
Version: 0.2.3
Summary: Laravel-style project structure for FastAPI
Author-email: Pradipta Bhuin <bhuinjohn@gmail.com>
License-Expression: MIT
Requires-Python: >=3.8
License-File: LICENSE
Requires-Dist: fastapi
Requires-Dist: uvicorn
Requires-Dist: sqlalchemy
Requires-Dist: pymysql
Requires-Dist: python-dotenv
Requires-Dist: alembic
Requires-Dist: click
Requires-Dist: pydantic[email]
Dynamic: license-file
